holdingsparser/__init__.py
holdingsparser/__main__.py
holdingsparser/application.py
holdingsparser/file.py
holdingsparser/scrape.py
holdingsparser/sec.py
holdingsparser-3.0.3.dist-info/entry_points.txt
holdingsparser-3.0.3.dist-info/LICENSE
holdingsparser-3.0.3.dist-info/WHEEL
holdingsparser-3.0.3.dist-info/METADATA
holdingsparser-3.0.3.dist-info/RECORD
