Metadata-Version: 2.1
Name: holdingsparser
Version: 3.0.3
Summary: A program that parses 13F reports filed with the SEC.
Home-page: https://github.com/mhadam/holdingsparser
License: MIT
Author: mhadam
Author-email: michael@hadam.us
Requires-Python: >=3.9,<4.0
Classifier: License :: OSI Approved :: MIT License
Classifier: Programming Language :: Python :: 3
Classifier: Programming Language :: Python :: 3.9
Requires-Dist: beautifulsoup4 (>=4.9.3,<5.0.0)
Requires-Dist: requests (>=2.25.1,<3.0.0)
Requires-Dist: requests-random-user-agent (>=2021.4.10,<2022.0.0)
Requires-Dist: typer[all] (>=0.3.2,<0.4.0)
Requires-Dist: untangle (>=1.1.1,<2.0.0)
Project-URL: Repository, https://github.com/mhadam/holdingsparser
